cdbclerk/__init__.py
cdbclerk/__main__.py
cdbclerk/_version.py
cdbclerk/ioc_io.py
cdbclerk/store_fields.py
cdbclerk/tests/__init__.py
cdbclerk/tests/conftest.py
cdbclerk/tests/test_read_pvs.py
cdbclerk-0.1.dist-info/AUTHORS.rst
cdbclerk-0.1.dist-info/LICENSE
cdbclerk-0.1.dist-info/METADATA
cdbclerk-0.1.dist-info/WHEEL
cdbclerk-0.1.dist-info/entry_points.txt
cdbclerk-0.1.dist-info/top_level.txt
cdbclerk-0.1.dist-info/RECORD
